{"index.md":"BTSVEJBa","page.md":"DoABcoOA","page_1.md":"CiCVmKo6","page_2.md":"CJscnRLx","page_index.md":"BxxJNx7d","pages_about.md":"BLWLX-y_","pages_archives.md":"D1TbePKt","pages_categories.md":"JR1hZzk3","pages_categories_光设理论基础.md":"DEbFD0IM","pages_categories_光设软件基础-zemax.md":"BwuxOUpx","pages_categories_全景环带光学系统.md":"CaIpL5EB","pages_categories_随便说说.md":"D80bcS1O","pages_cc.md":"CCf5sR18","pages_index.md":"sXXv2oCD","pages_link.md":"Dkg5ApA4","pages_privacy.md":"Cijnu5Db","pages_project.md":"Cd6coZO2","pages_tags.md":"BI0ew_uo","pages_tags_aberrations.md":"7-BIgeDR","pages_tags_hello.md":"CjXHubLw","pages_tags_zemax.md":"hCfOK2iq","pages_tags_光学系统设计.md":"BgAsqvkA","pages_tags_基础理论.md":"COX8pFtq","posts_2024_1010.md":"vf0H0lFx","posts_2025_aberrations chapter1-basic concepts in geometrical optics.md":"CA_UMAFl","posts_2025_designing optics using zemax  chapter7 coma and astigmatism（彗差与像散）.md":"DQKMRdWN","posts_2025_designing optics using zemax chapter5 stops_pupils_windows.md":"CiiQR00z","posts_2025_designing optics using zemax chapter6 spherical aberration.md":"rJik2hWM","posts_2025_ray geometrical optics-chapter3 optical aberrations 光学像差.md":"k1HvL68j","posts_2025_光学系统设计第一章①-费马原理与高斯光学.md":"CyoNQ6ba","posts_2025_光学系统设计第一章②-程函方程式、波动光学与几何光学的联系.md":"Iy6iUEJt","posts_2025_光学系统设计第二章①-初级像差理论.md":"4BI09J9I","posts_2025_光学系统设计第二章②初级像差及其光束结构.md":"BYnjeuwc","posts_2025_全景环带光学系统—面临的挑战与设计参数.md":"S06P7Qy6"}
